roseau/load_flow/__about__.py
roseau/load_flow/__init__.py
roseau/load_flow/_solvers.py
roseau/load_flow/constants.py
roseau/load_flow/converters.py
roseau/load_flow/data/io/DGS-RLF.pfd
roseau/load_flow/data/lines/Catalogue.csv
roseau/load_flow/data/networks/Catalogue.json
roseau/load_flow/data/networks/LVFeeder00939_Summer.json
roseau/load_flow/data/networks/LVFeeder00939_Winter.json
roseau/load_flow/data/networks/LVFeeder02639_Summer.json
roseau/load_flow/data/networks/LVFeeder02639_Winter.json
roseau/load_flow/data/networks/LVFeeder04790_Summer.json
roseau/load_flow/data/networks/LVFeeder04790_Winter.json
roseau/load_flow/data/networks/LVFeeder06713_Summer.json
roseau/load_flow/data/networks/LVFeeder06713_Winter.json
roseau/load_flow/data/networks/LVFeeder06926_Summer.json
roseau/load_flow/data/networks/LVFeeder06926_Winter.json
roseau/load_flow/data/networks/LVFeeder06975_Summer.json
roseau/load_flow/data/networks/LVFeeder06975_Winter.json
roseau/load_flow/data/networks/LVFeeder18498_Summer.json
roseau/load_flow/data/networks/LVFeeder18498_Winter.json
roseau/load_flow/data/networks/LVFeeder18769_Summer.json
roseau/load_flow/data/networks/LVFeeder18769_Winter.json
roseau/load_flow/data/networks/LVFeeder19558_Summer.json
roseau/load_flow/data/networks/LVFeeder19558_Winter.json
roseau/load_flow/data/networks/LVFeeder20256_Summer.json
roseau/load_flow/data/networks/LVFeeder20256_Winter.json
roseau/load_flow/data/networks/LVFeeder23832_Summer.json
roseau/load_flow/data/networks/LVFeeder23832_Winter.json
roseau/load_flow/data/networks/LVFeeder24400_Summer.json
roseau/load_flow/data/networks/LVFeeder24400_Winter.json
roseau/load_flow/data/networks/LVFeeder27429_Summer.json
roseau/load_flow/data/networks/LVFeeder27429_Winter.json
roseau/load_flow/data/networks/LVFeeder27681_Summer.json
roseau/load_flow/data/networks/LVFeeder27681_Winter.json
roseau/load_flow/data/networks/LVFeeder30216_Summer.json
roseau/load_flow/data/networks/LVFeeder30216_Winter.json
roseau_load_flow-0.14.0.dist-info/WHEEL
roseau_load_flow-0.14.0.dist-info/METADATA
roseau_load_flow-0.14.0.dist-info/RECORD
