Metadata-Version: 2.3
Name: roseau-load-flow
Version: 0.14.0
Summary: Highly capable multi-phase load flow solver
Author: Ali Hamdan, Sébastien Vallet, Benoît Vinot, Florent Cadoux, Louise Muller, Audrey Ficot, Victor Gouin
Author-email: Ali Hamdan <ali.hamdan@roseautechnologies.com>, Sébastien Vallet <sebastien.vallet@roseautechnologies.com>, Benoît Vinot <benoit.vinot@roseautechnologies.com>, Florent Cadoux <florent.cadoux@roseautechnologies.com>, Louise Muller <louise.muller@roseautechnologies.com>, Audrey Ficot <audrey.ficot@roseautechnologies.com>
License: BSD 3-Clause License
Classifier: Development Status :: 3 - Alpha
Classifier: Operating System :: MacOS :: MacOS X
Classifier: Operating System :: Microsoft :: Windows
Classifier: Operating System :: POSIX :: Linux
Classifier: Programming Language :: Python :: 3.12
Classifier: Programming Language :: Python :: 3.13
Classifier: Programming Language :: Python :: 3.14
Classifier: Programming Language :: Python :: Free Threading :: 2 - Beta
Classifier: Topic :: Scientific/Engineering :: Physics
Requires-Dist: certifi>=2023.5.7
Requires-Dist: geopandas>=1.0.0
Requires-Dist: numpy>=2.0.0
Requires-Dist: pandas>=2.1.0
Requires-Dist: pint>=0.21.0
Requires-Dist: platformdirs>=4.0.0
Requires-Dist: pyproj>=3.3.0
Requires-Dist: roseau-load-flow-engine==0.19.0
Requires-Dist: shapely>=2.0.0
Requires-Dist: typing-extensions>=4.6.2
Requires-Dist: networkx>=3.3.0 ; extra == 'graph'
Requires-Dist: matplotlib>=3.9.0 ; extra == 'plot'
Maintainer: Ali Hamdan
Maintainer-email: Ali Hamdan <ali.hamdan@roseautechnologies.com>
Requires-Python: >=3.12
Project-URL: documentation, https://roseau-load-flow.roseautechnologies.com/
Project-URL: homepage, https://www.roseautechnologies.com/roseau-load-flow/
Project-URL: issues, https://github.com/RoseauTechnologies/Roseau_Load_Flow/issues/
Project-URL: repository, https://github.com/RoseauTechnologies/Roseau_Load_Flow/
Provides-Extra: graph
Provides-Extra: plot
